setup.py
fief/__init__.py
fief/fief.py
fief/info.py
fief.egg-info/PKG-INFO
fief.egg-info/SOURCES.txt
fief.egg-info/dependency_links.txt
fief.egg-info/top_level.txt
fief/test/__init__.py
fief/test/test_fief.py