Metadata-Version: 1.1
Name: fief
Version: 1.0.1
Summary: Decorator for effective parameter filtering
Home-page: https://github.com/Aluriak/fief
Author: lucas
Author-email: lucas.bourneuf@laposte.net
License: UNKNOWN
Keywords: decorator parameter filter
Platform: UNKNOWN
Classifier: License :: OSI Approved :: GNU General Public License (GPL)
Classifier: Natural Language :: English
Classifier: Operating System :: Unix
Classifier: Programming Language :: Python :: 3
Classifier: Topic :: Software Development :: Libraries :: Python Modules
